setup.py
Flasky_Micro.egg-info/PKG-INFO
Flasky_Micro.egg-info/SOURCES.txt
Flasky_Micro.egg-info/dependency_links.txt
Flasky_Micro.egg-info/not-zip-safe
Flasky_Micro.egg-info/requires.txt
Flasky_Micro.egg-info/top_level.txt
flasky/__init__.py
flasky/configuration.py
flasky/exceptions.py
flasky/globalizer.py
flasky/log.py
flasky/server.py
flasky/view.py