Metadata-Version: 1.0
Name: Flasky-Micro
Version: 1.0.1
Summary: Flask Micro Service Framework
Home-page: UNKNOWN
Author: Mathieu Paul
Author-email: laup.mathieu@gmail.com
License: MIT
Platform: UNKNOWN
